odoo10_addon_account_move_line_tax_editable-10.0.1.0.1.99.dev5-py2.7-nspkg.pth
odoo/addons/account_move_line_tax_editable/README.rst
odoo/addons/account_move_line_tax_editable/__init__.py
odoo/addons/account_move_line_tax_editable/__manifest__.py
odoo/addons/account_move_line_tax_editable/i18n/account_move_line_tax_editable.pot
odoo/addons/account_move_line_tax_editable/i18n/de.po
odoo/addons/account_move_line_tax_editable/i18n/es_EC.po
odoo/addons/account_move_line_tax_editable/i18n/hr.po
odoo/addons/account_move_line_tax_editable/i18n/tr_TR.po
odoo/addons/account_move_line_tax_editable/models/__init__.py
odoo/addons/account_move_line_tax_editable/models/account_move_line.py
odoo/addons/account_move_line_tax_editable/static/description/icon.png
odoo/addons/account_move_line_tax_editable/views/account_move.xml
odoo/addons/account_move_line_tax_editable/views/account_move_line.xml
odoo10_addon_account_move_line_tax_editable-10.0.1.0.1.99.dev5.dist-info/METADATA
odoo10_addon_account_move_line_tax_editable-10.0.1.0.1.99.dev5.dist-info/RECORD
odoo10_addon_account_move_line_tax_editable-10.0.1.0.1.99.dev5.dist-info/WHEEL
odoo10_addon_account_move_line_tax_editable-10.0.1.0.1.99.dev5.dist-info/namespace_packages.txt
odoo10_addon_account_move_line_tax_editable-10.0.1.0.1.99.dev5.dist-info/top_level.txt
