Metadata-Version: 2.1
Name: odoo10-addon-account-move-line-tax-editable
Version: 10.0.1.0.1.99.dev5
Summary: Allows to edit taxes on non-posted account move lines
Home-page: https://www.acsone.eu
Author: ACSONE SA/NV,Odoo Community Association (OCA)
Author-email: support@odoo-community.org
License: AGPL-3
Platform: UNKNOWN
Classifier: Programming Language :: Python
Classifier: Framework :: Odoo
Classifier: License :: OSI Approved :: GNU Affero General Public License v3
Requires-Python: ~=2.7
Requires-Dist: odoo (<10.1dev,>=10.0)
